botco/__init__.py
botco/bot.py
botco/contrib/__init__.py
botco/contrib/builtin_filters.py
botco/contrib/fsm.py
botco/contrib/handler.py
botco/contrib/middlewares.py
botco/contrib/mixin.py
botco/contrib/session.py
botco/contrib/storage.py
botco/contrib/thread_pool.py
botco/dispatcher.py
botco/filters.py
botco/methods/__init__.py
botco/methods/add_sticker_to_set.py
botco/methods/answer_callback_query.py
botco/methods/answer_inline_query.py
botco/methods/answer_pre_checkout_query.py
botco/methods/answer_shipping_query.py
botco/methods/approve_chat_join_request.py
botco/methods/ban_chat_member.py
botco/methods/base.py
botco/methods/close.py
botco/methods/copy_message.py
botco/methods/create_chat_invite_link.py
botco/methods/create_new_sticker_set.py
botco/methods/decline_chat_join_request.py
botco/methods/delete_chat_photo.py
botco/methods/delete_chat_sticker_set.py
botco/methods/delete_message.py
botco/methods/delete_my_commands.py
botco/methods/delete_sticker_from_set.py
botco/methods/delete_webhook.py
botco/methods/edit_chat_invite_link.py
botco/methods/edit_message_caption.py
botco/methods/edit_message_live_location.py
botco/methods/edit_message_media.py
botco/methods/edit_message_reply_markup.py
botco/methods/edit_message_text.py
botco/methods/export_chat_invite_link.py
botco/methods/forward_message.py
botco/methods/get_chat.py
botco/methods/get_chat_administrators.py
botco/methods/get_chat_member.py
botco/methods/get_chat_member_count.py
botco/methods/get_chat_members_count.py
botco/methods/get_file.py
botco/methods/get_game_high_scores.py
botco/methods/get_me.py
botco/methods/get_my_commands.py
botco/methods/get_sticker_set.py
botco/methods/get_updates.py
botco/methods/get_user_profile_photos.py
botco/methods/get_webhook_info.py
botco/methods/kick_chat_member.py
botco/methods/leave_chat.py
botco/methods/log_out.py
botco/methods/pin_chat_message.py
botco/methods/promote_chat_member.py
botco/methods/restrict_chat_member.py
botco/methods/revoke_chat_invite_link.py
botco-0.1.3.dist-info/LICENSE
botco-0.1.3.dist-info/WHEEL
botco-0.1.3.dist-info/METADATA
botco-0.1.3.dist-info/RECORD
